LICENSE
MANIFEST.in
README.rst
setup.py
version.py
exceltowiki/__init__.py
exceltowiki.egg-info/PKG-INFO
exceltowiki.egg-info/SOURCES.txt
exceltowiki.egg-info/dependency_links.txt
exceltowiki.egg-info/not-zip-safe
exceltowiki.egg-info/requires.txt
exceltowiki.egg-info/top_level.txt
exceltowiki/example/__init__.py
exceltowiki/example/example.py
exceltowiki/example/test.xlsx