Metadata-Version: 1.0
Name: exceltowiki
Version: 0.1.16
Summary: Convert Excel to Wiki while maintaining formatting
Home-page: http://github.com/venkman69/ExcelToWiki
Author: Narayan Natarajan
Author-email: venkman69@yahoo.com
License: MIT
Platform: UNKNOWN
